selenium_helpers/__init__.py
selenium_helpers-1.0.5.dist-info/LICENSE
selenium_helpers-1.0.5.dist-info/METADATA
selenium_helpers-1.0.5.dist-info/WHEEL
selenium_helpers-1.0.5.dist-info/top_level.txt
selenium_helpers-1.0.5.dist-info/RECORD
