Metadata-Version: 2.1
Name: selenium-helpers
Version: 1.0.5
Summary: Tools to make certain selenium tasks more straightforward.
Home-page: https://github.com/ExSidius/selenium_helpers
Author: ExSidius
Author-email: mukul.ram97@gmail.com
License: MIT
Platform: UNKNOWN
License-File: LICENSE
Requires-Dist: selenium
